veracode_to_sqlite/__init__.py
veracode_to_sqlite/__main__.py
veracode_to_sqlite/database.py
veracode_to_sqlite/model.py
veracode_to_sqlite-0.1.4.dist-info/entry_points.txt
veracode_to_sqlite-0.1.4.dist-info/LICENSE
veracode_to_sqlite-0.1.4.dist-info/WHEEL
veracode_to_sqlite-0.1.4.dist-info/METADATA
veracode_to_sqlite-0.1.4.dist-info/RECORD
