Metadata-Version: 2.1
Name: veracode-to-sqlite
Version: 0.1.4
Summary: Create a SQLite database from a Veracode results file.
License: MPL 2.0
Author: Nathaniel Knight
Author-email: nathaniel.ep@gmail.com
Requires-Python: >=3.7,<4.0
Classifier: License :: Other/Proprietary License
Classifier: Programming Language :: Python :: 3
Classifier: Programming Language :: Python :: 3.10
Classifier: Programming Language :: Python :: 3.7
Classifier: Programming Language :: Python :: 3.8
Classifier: Programming Language :: Python :: 3.9
